shortcut_tool/__init__.py
shortcut_tool/__main__.py
shortcut_tool-1.0.3.dist-info/LICENSE
shortcut_tool-1.0.3.dist-info/METADATA
shortcut_tool-1.0.3.dist-info/WHEEL
shortcut_tool-1.0.3.dist-info/top_level.txt
shortcut_tool-1.0.3.dist-info/RECORD
